gunit/GUnit.py
gunit/__init__.py
gunit/execute.gdb
gunit/setup.gdb
gunit-0.1.59.data/scripts/gunit-cascade
gunit-0.1.59.data/scripts/gunit-gdbserver
gunit-0.1.59.data/scripts/gunit-header
gunit-0.1.59.data/scripts/gunit-openocd
gunit-0.1.59.dist-info/LICENSE
gunit-0.1.59.dist-info/METADATA
gunit-0.1.59.dist-info/WHEEL
gunit-0.1.59.dist-info/top_level.txt
gunit-0.1.59.dist-info/RECORD
