Metadata-Version: 2.1
Name: gunit
Version: 0.1.59
Summary: App for unit testing with GDB
Home-page: https://github.com/estcube/GUnit
Author: Mathias Plans
Author-email: mathiasplans15@gmail.com
License: MIT
Platform: UNKNOWN
Requires-Dist: junit-xml
